odoo/addons/l10n_nl_bank/README.rst
odoo/addons/l10n_nl_bank/__init__.py
odoo/addons/l10n_nl_bank/__manifest__.py
odoo/addons/l10n_nl_bank/data/res_bank_data.xml
odoo/addons/l10n_nl_bank/i18n/l10n_nl_bank.pot
odoo/addons/l10n_nl_bank/migrations/13.0.1.1.0/post-migration.py
odoo/addons/l10n_nl_bank/migrations/13.0.1.1.0/pre-migration.py
odoo/addons/l10n_nl_bank/readme/CONTRIBUTORS.rst
odoo/addons/l10n_nl_bank/readme/CREDITS.rst
odoo/addons/l10n_nl_bank/readme/DESCRIPTION.rst
odoo/addons/l10n_nl_bank/static/description/icon.png
odoo/addons/l10n_nl_bank/static/description/icon.svg
odoo/addons/l10n_nl_bank/static/description/index.html
odoo13_addon_l10n_nl_bank-13.0.1.1.1.dev2.dist-info/METADATA
odoo13_addon_l10n_nl_bank-13.0.1.1.1.dev2.dist-info/WHEEL
odoo13_addon_l10n_nl_bank-13.0.1.1.1.dev2.dist-info/top_level.txt
odoo13_addon_l10n_nl_bank-13.0.1.1.1.dev2.dist-info/RECORD
